LICENSE
MANIFEST.in
README.md
setup.py
messaging_app/__init__.py
messaging_app/messaging_app.py
messaging_app/messaging_app_config.py
messaging_app.egg-info/PKG-INFO
messaging_app.egg-info/SOURCES.txt
messaging_app.egg-info/dependency_links.txt
messaging_app.egg-info/entry_points.txt
messaging_app.egg-info/not-zip-safe
messaging_app.egg-info/requires.txt
messaging_app.egg-info/top_level.txt
messaging_app/db/messages/README.md
messaging_app/func/create_new_rsa.py
messaging_app/func/create_new_user.py
messaging_app/func/decrypt.py
messaging_app/func/encrypt.py
messaging_app/func/gen_keys.py
messaging_app/func/get.py
messaging_app/func/integration.py
messaging_app/func/message.py
messaging_app/func/miller_rabin.py
messaging_app/func/save_new_message.py
messaging_app/func/send.py
messaging_app/lib/keys_system.py
messaging_app/lib/messages_system.py
messaging_app/web/chat.py
messaging_app/web/static/HELP-US-OUT.txt
messaging_app/web/static/css/font-awesome.css
messaging_app/web/static/css/font-awesome.min.css
messaging_app/web/static/css/main.css
messaging_app/web/static/fonts/FontAwesome.otf
messaging_app/web/static/fonts/fontawesome-webfont.eot
messaging_app/web/static/fonts/fontawesome-webfont.svg
messaging_app/web/static/fonts/fontawesome-webfont.ttf
messaging_app/web/static/fonts/fontawesome-webfont.woff
messaging_app/web/static/fonts/fontawesome-webfont.woff2
messaging_app/web/static/image/cool-emoji.png
messaging_app/web/static/less/animated.less
messaging_app/web/static/less/bordered-pulled.less
messaging_app/web/static/less/core.less
messaging_app/web/static/less/fixed-width.less
messaging_app/web/static/less/font-awesome.less
messaging_app/web/static/less/icons.less
messaging_app/web/static/less/larger.less
messaging_app/web/static/less/list.less
messaging_app/web/static/less/mixins.less
messaging_app/web/static/less/path.less
messaging_app/web/static/less/rotated-flipped.less
messaging_app/web/static/less/screen-reader.less
messaging_app/web/static/less/stacked.less
messaging_app/web/static/less/variables.less
messaging_app/web/static/scss/_animated.scss
messaging_app/web/static/scss/_bordered-pulled.scss
messaging_app/web/static/scss/_core.scss
messaging_app/web/static/scss/_fixed-width.scss
