Metadata-Version: 2.1
Name: messaging-app
Version: 0.1.7
Summary: Messaging App
Home-page: https://github.com/Naruno/Messaging-App
Author: Naruno Developers
Author-email: onur.atakan.ulusoy@naruno.org
License: MIT
Platform: UNKNOWN
Requires-Python: >= 3
